CHANGELOG
LICENSE
LICENSE.3RDPARTY
MANIFEST.in
README.md
requirements-min-django.txt
requirements-test.txt
requirements.txt
setup.py
django_helpdesk3000.egg-info/PKG-INFO
django_helpdesk3000.egg-info/SOURCES.txt
django_helpdesk3000.egg-info/dependency_links.txt
django_helpdesk3000.egg-info/not-zip-safe
django_helpdesk3000.egg-info/requires.txt
django_helpdesk3000.egg-info/top_level.txt
helpdesk/__init__.py
helpdesk/admin.py
helpdesk/akismet.py
helpdesk/apps.py
helpdesk/forms.py
helpdesk/lib.py
helpdesk/models.py
helpdesk/settings.py
helpdesk/urls.py
helpdesk/fixtures/initial_data.json
helpdesk/locale/de/LC_MESSAGES/django.mo
helpdesk/locale/de/LC_MESSAGES/django.po
helpdesk/locale/el/LC_MESSAGES/django.mo
helpdesk/locale/el/LC_MESSAGES/django.po
helpdesk/locale/en/LC_MESSAGES/django.mo
helpdesk/locale/en/LC_MESSAGES/django.po
helpdesk/locale/es/LC_MESSAGES/django.mo
helpdesk/locale/es/LC_MESSAGES/django.po
helpdesk/locale/es_CO/LC_MESSAGES/django.mo
helpdesk/locale/es_CO/LC_MESSAGES/django.po
helpdesk/locale/es_MX/LC_MESSAGES/django.mo
helpdesk/locale/es_MX/LC_MESSAGES/django.po
helpdesk/locale/fa_IR/LC_MESSAGES/django.mo
helpdesk/locale/fa_IR/LC_MESSAGES/django.po
helpdesk/locale/fi/LC_MESSAGES/django.mo
helpdesk/locale/fi/LC_MESSAGES/django.po
helpdesk/locale/fr/LC_MESSAGES/django.mo
helpdesk/locale/fr/LC_MESSAGES/django.po
helpdesk/locale/hu/LC_MESSAGES/django.mo
helpdesk/locale/hu/LC_MESSAGES/django.po
helpdesk/locale/it/LC_MESSAGES/django.mo
helpdesk/locale/it/LC_MESSAGES/django.po
helpdesk/locale/nb_NO/LC_MESSAGES/django.mo
helpdesk/locale/nb_NO/LC_MESSAGES/django.po
helpdesk/locale/pl/LC_MESSAGES/django.mo
helpdesk/locale/pl/LC_MESSAGES/django.po
helpdesk/locale/pt_BR/LC_MESSAGES/django.mo
helpdesk/locale/pt_BR/LC_MESSAGES/django.po
helpdesk/locale/ru/LC_MESSAGES/django.mo
helpdesk/locale/ru/LC_MESSAGES/django.po
helpdesk/locale/sv/LC_MESSAGES/django.mo
helpdesk/locale/sv/LC_MESSAGES/django.po
helpdesk/locale/zh_CN/LC_MESSAGES/django.mo
helpdesk/locale/zh_CN/LC_MESSAGES/django.po
helpdesk/management/__init__.py
helpdesk/management/commands/__init__.py
helpdesk/management/commands/create_escalation_exclusions.py
helpdesk/management/commands/create_usersettings.py
