Metadata-Version: 1.1
Name: django-helpdesk3000
Version: 0.3.4
Summary: Django-powered ticket tracker for your helpdesk
Home-page: https://github.com/chrisspen/django-helpdesk3000
Author: Chris Spencer
Author-email: chrisspen@gmail.com
License: BSD
Keywords: django,helpdesk,tickets,incidents,cases
Platform: UNKNOWN
Classifier: Programming Language :: Python
Classifier: Topic :: Software Development :: Libraries :: Python Modules
Classifier: Framework :: Django
Classifier: Environment :: Web Environment
Classifier: Operating System :: OS Independent
Classifier: Intended Audience :: Customer Service
Classifier: License :: OSI Approved :: BSD License
Classifier: Natural Language :: English
Classifier: Topic :: Office/Business
Classifier: Topic :: Software Development :: Bug Tracking
